logfrog/__init__.py
logfrog/logfrog.py
logfrog-1.0.0.dist-info/LICENSE.txt
logfrog-1.0.0.dist-info/METADATA
logfrog-1.0.0.dist-info/WHEEL
logfrog-1.0.0.dist-info/top_level.txt
logfrog-1.0.0.dist-info/RECORD
