Metadata-Version: 2.1
Name: logfrog
Version: 1.0.0
Summary: A simple and efficient logging package in python with async support
Home-page: https://github.com/fuushyn/logfrog
Author: Lakshya Gupta
Classifier: License :: OSI Approved :: MIT License
Classifier: Programming Language :: Python :: 3
Classifier: Operating System :: OS Independent
License-File: LICENSE.txt
